odoo/addons/mrp_default_workorder_time/README.rst
odoo/addons/mrp_default_workorder_time/__init__.py
odoo/addons/mrp_default_workorder_time/__manifest__.py
odoo/addons/mrp_default_workorder_time/i18n/es.po
odoo/addons/mrp_default_workorder_time/i18n/hr.po
odoo/addons/mrp_default_workorder_time/i18n/it.po
odoo/addons/mrp_default_workorder_time/i18n/mrp_default_workorder_time.pot
odoo/addons/mrp_default_workorder_time/models/__init__.py
odoo/addons/mrp_default_workorder_time/models/company.py
odoo/addons/mrp_default_workorder_time/models/res_config_settings.py
odoo/addons/mrp_default_workorder_time/models/workorder.py
odoo/addons/mrp_default_workorder_time/readme/CONTRIBUTORS.rst
odoo/addons/mrp_default_workorder_time/readme/DESCRIPTION.rst
odoo/addons/mrp_default_workorder_time/readme/USAGE.rst
odoo/addons/mrp_default_workorder_time/static/description/icon.png
odoo/addons/mrp_default_workorder_time/static/description/index.html
odoo/addons/mrp_default_workorder_time/tests/__init__.py
odoo/addons/mrp_default_workorder_time/tests/test_workorder_times.py
odoo/addons/mrp_default_workorder_time/views/res_config_settings_view.xml
odoo_addon_mrp_default_workorder_time-16.0.1.0.0.8.dist-info/METADATA
odoo_addon_mrp_default_workorder_time-16.0.1.0.0.8.dist-info/WHEEL
odoo_addon_mrp_default_workorder_time-16.0.1.0.0.8.dist-info/top_level.txt
odoo_addon_mrp_default_workorder_time-16.0.1.0.0.8.dist-info/RECORD
